eztao/__init__.py
eztao/carma/CARMATerm.py
eztao/carma/__init__.py
eztao/carma/model_utils.py
eztao/ts/__init__.py
eztao/ts/carma_fit.py
eztao/ts/carma_mcmc.py
eztao/ts/carma_sim.py
eztao/ts/utils.py
eztao/viz/__init__.py
eztao/viz/eztao.rc
eztao/viz/mpl_viz.py
eztao-0.4.4.dist-info/LICENSE
eztao-0.4.4.dist-info/METADATA
eztao-0.4.4.dist-info/WHEEL
eztao-0.4.4.dist-info/RECORD
