Metadata-Version: 2.3
Name: eztao
Version: 0.4.4
Summary: A toolkit for Active Galactic Nuclei (AGN) time-series analysis.
License: MIT
Author: Weixiang Yu
Author-email: astro.flyfish@gmail.com
Requires-Python: >=3.9,<4.0
Classifier: License :: OSI Approved :: MIT License
Classifier: Programming Language :: Python :: 3
Classifier: Programming Language :: Python :: 3.9
Classifier: Programming Language :: Python :: 3.10
Classifier: Programming Language :: Python :: 3.11
Classifier: Programming Language :: Python :: 3.12
Classifier: Programming Language :: Python :: 3.13
Requires-Dist: celerite (>=0.3.0)
Requires-Dist: docutils (>=0.21.2,<0.22.0)
Requires-Dist: emcee (>=3.0.0)
Requires-Dist: importlib-metadata (>=2.0.0)
Requires-Dist: matplotlib (>=3.3.0,<4.0.0)
Requires-Dist: numba (>=0.57.0)
Requires-Dist: numpy (>=1.26,<2.0)
Requires-Dist: scipy (>=1.5)
Project-URL: Repository, https://github.com/ywx649999311/EzTao
